LICENSE
README.md
setup.py
src/cloud_client/__init__.py
src/cloud_client/azure.py
src/cloud_explorer.egg-info/PKG-INFO
src/cloud_explorer.egg-info/SOURCES.txt
src/cloud_explorer.egg-info/dependency_links.txt
src/cloud_explorer.egg-info/requires.txt
src/cloud_explorer.egg-info/top_level.txt