Metadata-Version: 2.1
Name: cloud-explorer
Version: 0.0.0
Summary: A library offers some utilities to explore cloud resources
Home-page: UNKNOWN
Author: Mohamad Karam Kassem
Author-email: aram.kass@gmail.com
License: MIT License
Platform: UNKNOWN
License-File: LICENSE
